README.md
setup.py
key_pressing/__init__.py
key_pressing/posix.py
key_pressing.egg-info/PKG-INFO
key_pressing.egg-info/SOURCES.txt
key_pressing.egg-info/dependency_links.txt
key_pressing.egg-info/top_level.txt
key_pressing.egg-info/zip-safe